{"apiClass":"Model","author":"COMSOL","created":"1696135445354","description":"The example models cyclic voltammetry at an electrode of mm dimensions. In this common analytical electrochemistry technique, the potential at a working electrode is swept up and down and the current is recorded. The current-voltage waveform (the voltammogram) gives information about the reactivity and mass transport properties of the analyte.","displayLabel":"cyclic_voltammetry_1d.mph","icon":"comsol_modelroot.png","keyword":["tutorial"],"label":"cyclic_voltammetry_1d.mph","language":"en_US","lastComputationDate":"1696135425385","lastComputationTime":"8468","lastComputationVersion":"COMSOL 6.2.0.259","lastModified":"1696135445370","lastModifiedBy":"COMSOL","modelEntityPath":"/","name":"root","nodes":[{"apiClass":"NonEntity","icon":"global_branch.png","label":"Global Definitions","nodes":[{"apiClass":"ModelParamGroup","author":"COMSOL","created":"1696135407620","displayLabel":"Parameters 1","icon":"parameter.png","label":"Parameters 1","lastModified":"0","lastModifiedBy":"COMSOL","modelEntityPath":"/param/group/default","settings":[{"description":"Voltammetric scan rate","name":"v","scalarImag":"0.0","scalarReal":"1.0","value":"1[V/s]"},{"description":"Reactant bulk concentration","name":"c_bulk","scalarImag":"0.0","scalarReal":"1.0","value":"1[mmol/L]"},{"description":"Reactant diffusion coefficient","name":"DA","scalarImag":"0.0","scalarReal":"1.0E-9","value":"1e-9[m^2/s]"},{"description":"Product diffusion coefficient","name":"DB","scalarImag":"0.0","scalarReal":"1.0E-9","value":"1e-9[m^2/s]"},{"description":"Reaction rate (dimensionless)","name":"K0","scalarImag":"0.0","scalarReal":"1.0E10","value":"1e10"},{"description":"Electrode radius","name":"re","scalarImag":"0.0","scalarReal":"0.01","value":"10[mm]"},{"description":"Reference exchange current density","name":"i0ref","scalarImag":"0.0","scalarReal":"9.6485E10","value":"9.6485e10[A/m^2]"},{"description":"Double layer capacitance","name":"Cdl","scalarImag":"0.0","scalarReal":"0.2","value":"0.2[F/m^2]"},{"description":"Temperature","name":"T","scalarImag":"0.0","scalarReal":"298.15","value":"298.15[K]"},{"description":"Start potential","name":"E_vertex1","scalarImag":"0.0","scalarReal":"-0.4","value":"-0.4[V]"},{"description":"Switching potential","name":"E_vertex2","scalarImag":"0.0","scalarReal":"0.4","value":"0.4[V]"},{"description":"Outer bound on diffusion layer","name":"L","scalarImag":"0.0","scalarReal":"2.4000000000000003E-4","value":"6*sqrt(DA*2*abs(E_vertex1-E_vertex2)/v)"},{"description":"Initial product concentration at electrode","name":"cB0","scalarImag":"0.0","scalarReal":"1.7322000028970182E-7","value":"c_bulk/(1+exp(-E_vertex1*F_const/(R_const*T)))"}],"tag":"default","type":"Parameters","windowType":1},{"apiClass":"CommonFeature","apiType":"CommonInputDefault","author":"COMSOL","created":"1696135407620","displayLabel":"Default Model Inputs","icon":"commonmodelinput.png","label":"Default Model Inputs","lastModified":"0","lastModifiedBy":"COMSOL","modelEntityPath":"/common/cminpt","settings":[{"description":"Model input","name":"quantity","value":"temperature"}],"tag":"cminpt","type":"Default_model_inputs","windowType":1},{"apiClass":"MaterialList","author":"COMSOL","created":"1696135407620","displayLabel":"Materials","icon":"global_materials.png","label":"Materials","lastModified":"0","lastModifiedBy":"COMSOL","modelEntityPath":"/material","tag":"material","type":"Materials","windowType":1}],"tag":"nonEntity1","windowType":1},{"apiClass":"ModelNode","author":"COMSOL","axisymmetric":false,"created":"1696135407745","displayLabel":"Component 1","icon":"model_1d.png","label":"Component 1","lastModified":"0","lastModifiedBy":"COMSOL","modelEntityPath":"/modelNode/comp1","name":"comp1","nodes":[{"apiClass":"NonEntity","icon":"definitions.png","label":"Definitions","nodes":[{"apiClass":"View","apiType":"ModelView1D","author":"COMSOL","created":"1696135407745","displayLabel":"View 1","icon":"view3d.png","label":"View 1","lastModified":"0","lastModifiedBy":"COMSOL","modelEntityPath":"/view/view1","nodes":[{"apiClass":"ViewFeature","apiType":"Axis1D","author":"COMSOL","created":"1696135407745","displayLabel":"Axis","icon":"view_axis.png","label":"Axis","lastModified":"1696135421854","lastModifiedBy":"COMSOL","modelEntityPath":"/view/view1/axis","settings":[{"description":"x minimum","name":"xmin","scalarReal":"-1.200000406242907E-5","value":"-1.200000406242907E-5"},{"description":"x maximum","name":"xmax","scalarReal":"2.519999979995191E-4","value":"2.519999979995191E-4"},{"apiValue":"off","description":"Manual spacing","name":"manualgrid","value":"false"}],"tag":"axis","type":"Axis","windowType":1}],"settings":[{"apiValue":"off","description":"Show geometry labels","name":"showlabels","value":"false"},{"apiValue":"off","description":"Show edge direction arrows","name":"showDirections","value":"false"},{"apiValue":"on","description":"Show axis units","name":"showunits","value":"true"},{"apiValue":"off","description":"Lock axis","name":"locked","value":"false"}],"tag":"view1","type":"View","windowType":1}],"tag":"nonEntity2","windowType":1},{"apiClass":"GeomSequence","author":"COMSOL","axisymmetric":false,"created":"1696135407745","displayLabel":"Geometry 1","icon":"geometry.png","label":"Geometry 1","lastModified":"1696135423776","lastModifiedBy":"COMSOL","modelEntityPath":"/geom/geom1","nodes":[{"apiClass":"GeomFeature","apiType":"Interval","author":"COMSOL","created":"1696135410042","displayLabel":"Interval 1","icon":"interval.png","label":"Interval 1","lastModified":"1696135423776","lastModifiedBy":"COMSOL","modelEntityPath":"/geom/geom1/feature/i1","name":"i1","settings":[{"apiValue":"off","description":"Resulting objects selection","name":"selresult","value":"false"},{"apiValue":"coord","description":"Specify","name":"specify","value":"Coordinates"},{"apiValue":"table","description":"Coordinate source","name":"coordsource","value":"Table"}],"tag":"i1","type":"Interval","windowType":1},{"apiClass":"GeomFeature","apiType":"Finalize","author":"COMSOL","created":"1696135407745","displayLabel":"Form Union","icon":"geom_form_union_assembly.png","label":"Form Union","lastModified":"1696135423776","lastModifiedBy":"COMSOL","modelEntityPath":"/geom/geom1/feature/fin","name":"fin","settings":[{"apiValue":"union","description":"Action","name":"action","value":"Form a union"},{"apiValue":"auto","description":"Repair tolerance","name":"repairtoltype","value":"Automatic"}],"tag":"fin","type":"Form_union/assembly","windowType":1}],"settings":[{"apiValue":"off","description":"Scale values when changing units","name":"scale","value":"false"},{"apiValue":"m","description":"Length unit","name":"lengthunit","value":"m"},{"apiValue":"deg","description":"Angular unit","name":"angularunit","value":"Degrees"},{"apiValue":"auto","description":"Default repair tolerance","name":"repairtoltype","value":"Automatic"},{"apiValue":"on","description":"Build new operations automatically","name":"autoBuildNew","value":"true"},{"apiValue":"on","description":"Build automatically when leaving geometry","name":"autorebuild","value":"true"}],"spaceDimension":1,"tag":"geom1","type":"Geometry","windowType":1},{"apiClass":"Physics","apiType":"TertiaryElectroanalysis","author":"COMSOL","created":"1696135407761","displayLabel":"Electroanalysis","icon":"phys_electroanalysis.png","label":"Electroanalysis","lastModified":"0","lastModifiedBy":"COMSOL","modelEntityPath":"/physics/tcd","name":"tcd","nodes":[{"apiClass":"PhysicsFeature","apiType":"Electrolyte","author":"COMSOL","created":"1696135407792","displayLabel":"Electrolyte 1","icon":"domainlevel_1d.png","label":"Electrolyte 1","lastModified":"0","lastModifiedBy":"COMSOL","modelEntityPath":"/physics/tcd/feature/ice1","settings":[{"apiValue":"userdef","description":"Velocity field","name":"u_src","value":"User defined"},{"apiValue":"none","description":"Material","name":"DiffusionMaterialList","value":"None"},{"apiValue":"userdef","description":"Diffusion coefficient","name":"D_cA_mat","value":"User defined"},{"name":"D_cA","value":"DA"},{"apiValue":"userdef","description":"Diffusion coefficient","name":"D_cB_mat","value":"User defined"},{"name":"D_cB","value":"DB"},{"apiValue":"GlobalSystem","description":"Coordinate system","name":"coordinateSystem","value":"Global coordinate system"},{"apiValue":"fromCommonDef","description":"Temperature","name":"minput_temperature_src","value":"Common model input"}],"tag":"ice1","type":"Electrolyte","windowType":1},{"apiClass":"PhysicsFeature","apiType":"NoFlux","author":"COMSOL","created":"1696135407792","displayLabel":"No Flux 1","icon":"boundarylevel_1d.png","label":"No Flux 1","lastModified":"0","lastModifiedBy":"COMSOL","modelEntityPath":"/physics/tcd/feature/nflx1","tag":"nflx1","type":"No_flux","windowType":1},{"apiClass":"PhysicsFeature","apiType":"ElectricInsulation","author":"COMSOL","created":"1696135407792","displayLabel":"Insulation 1","icon":"boundarylevel_1d.png","label":"Insulation 1","lastModified":"0","lastModifiedBy":"COMSOL","modelEntityPath":"/physics/tcd/feature/ein1","tag":"ein1","type":"Insulation","windowType":1},{"apiClass":"PhysicsFeature","apiType":"init","author":"COMSOL","created":"1696135407792","displayLabel":"Initial Values 1","icon":"domainlevel_1d.png","label":"Initial Values 1","lastModified":"0","lastModifiedBy":"COMSOL","modelEntityPath":"/physics/tcd/feature/init1","settings":[{"name":"initphis","scalarReal":"0.0","value":"0"}],"tag":"init1","type":"Initial_values","windowType":1},{"apiClass":"PhysicsFeature","apiType":"Concentration","author":"COMSOL","created":"1696135411901","displayLabel":"Concentration 1","icon":"boundarylevel_1d.png","label":"Concentration 1","lastModified":"0","lastModifiedBy":"COMSOL","modelEntityPath":"/physics/tcd/feature/conc1","settings":[{"apiValue":"pointwiseConstraints","description":"Constraint","name":"constraintOptions","value":"Pointwise constraints"},{"apiValue":"symmetricConstraint","description":"Apply reaction terms on","name":"constraintType","value":"All physics (symmetric)"},{"apiValue":"elemental","description":"Constraint method","name":"constraintMethod","value":"Elemental"},{"description":["Species cA","Species cB"],"name":"species"}],"tag":"conc1","type":"Concentration","windowType":1},{"apiClass":"PhysicsFeature","apiType":"ElectrodeSurface","author":"COMSOL","created":"1696135412386","displayLabel":"Electrode Surface 1","icon":"boundarylevel_1d.png","label":"Electrode Surface 1","lastModified":"0","lastModifiedBy":"COMSOL","modelEntityPath":"/physics/tcd/feature/es1","nodes":[{"apiClass":"PhysicsFeature","apiType":"ElectrodeReaction","author":"COMSOL","created":"1696135412401","displayLabel":"Electrode Reaction 1","icon":"boundarylevel_1d.png","label":"Electrode Reaction 1","lastModified":"0","lastModifiedBy":"COMSOL","modelEntityPath":"/physics/tcd/feature/es1/feature/er1","settings":[{"description":"Number of participating electrons","name":"nm","scalarReal":"1.0","value":"1"},{"name":"Eeq_ref","value":"0[V]"},{"apiValue":"NernstEquation","description":"Equilibrium potential","name":"Eeq_mat","value":"Nernst equation"},{"description":"Electrolyte species","name":"ElectrolyteSpecies"},{"apiValue":"ButlerVolmer","description":"Kinetics expression type","name":"ElectrodeKinetics","value":"Butler-Volmer"},{"apiValue":"MassActionLaw","description":"Exchange current density type","name":"i0Type","value":"Mass action law"},{"description":"Reference exchange current density","name":"i0_ref","value":"i0ref"},{"description":"Anodic transfer coefficient","name":"alphaa","scalarReal":"0.5","value":"0.5"},{"description":"Linearize concentration dependence for low concentrations","name":"LinearizeConcentrationDependence"},{"description":"Concentration linearization limit","name":"clim","value":"1e-3[mol/m^3]"},{"apiValue":"FromKineticsExpression","description":"Local current density expression","name":"ilocmat_mat","value":"From kinetics expression"},{"description":"Limiting current density","name":"LimitingCurrentDensity"},{"apiValue":"TemperatureDerivative","description":"Specify","name":"HeatofReactionType","value":"Temperature derivative"},{"apiValue":"userdef","description":"Temperature derivative of equilibrium potential","name":"dEeqdT_mat","value":"User defined"},{"name":"dEeqdT","scalarReal":"0.0","value":"0"},{"apiValue":"fromCommonDef","description":"Temperature","name":"minput_temperature_src","value":"Common model input"}],"tag":"er1","type":"Electrode_reaction","windowType":1},{"apiClass":"PhysicsFeature","apiType":"DoubleLayerCapacitance","author":"COMSOL","created":"1696135414495","displayLabel":"Double-Layer Capacitance 1","icon":"boundarylevel_1d.png","label":"Double-Layer Capacitance 1","lastModified":"0","lastModifiedBy":"COMSOL","modelEntityPath":"/physics/tcd/feature/es1/feature/dlc1","settings":[{"description":"Electrical double layer capacitance","name":"Cdl","value":"Cdl"},{"description":"Number of participating electrons","name":"nm","scalarReal":"1.0","value":"1"}],"tag":"dlc1","type":"Double_layer_capacitance","windowType":1}],"settings":[{"description":"Solve for surface concentration variables","name":"SolveForDissolvingDepositingConcentrationVariable"},{"description":"Species","name":"Species"},{"description":"Molar mass","name":"Ms"},{"description":"Density","name":"rhos"},{"description":"Density of sites","name":"Gamma","value":"1e-5[mol/m^2]"},{"description":"Adsorbing-desorbing species","name":"AdsorbingDesorbingSpecies"},{"description":"Site occupancy number","name":"Sigma"},{"apiValue":"NoFilmResistance","description":"Film resistance","name":"FilmResistanceType","value":"No film resistance"},{"apiValue":"CyclicVoltammetry","description":"Electrode phase potential condition","name":"BoundaryCondition","value":"Cyclic voltammetry"},{"description":"Perturbation amplitude","name":"deltaphisext","value":"0[V]"},{"description":"Linear sweep rate","name":"sweeprate","value":"v"},{"description":"Start potential","name":"EnableStartPotential"},{"description":"Number of cycles","name":"ncycle","scalarReal":"1.0","value":"1"},{"description":"Vertex potential 1","name":"Evertex1","value":"E_vertex1"},{"description":"Vertex potential 2","name":"Evertex2","value":"E_vertex2"},{"description":"End potential","name":"EnableEndPotential"},{"description":"Smoothing of cyclic voltammetry wave functions","name":"EnableTimeSmoothing"},{"description":"Smoothing factor","name":"smoothingfactor","scalarReal":"0.001","value":"1e-3"},{"description":"Add events at vertex potentials in cyclic voltammetry","name":"EnableVertexPotentialsEvents"},{"apiValue":"AvgAllReactions","description":"Equilibrium potential based on","name":"EqPotentialHandlingType","value":"Average of all reactions"}],"tag":"es1","type":"Electrode_surface","windowType":1}],"settings":[{"apiValue":"1","description":"Concentration","name":"order_concentration","value":"Linear"},{"apiValue":"2","description":"Electric potential","name":"order_electricpotential","value":"Quadratic"},{"apiValue":"Automatic","description":"Equation form","name":"form","value":"Study controlled"},{"name":"Ac","value":"1[m^2]"},{"apiValue":"Electroanalysis","description":"Charge conservation model","name":"ChargeTransportModel","value":"Electroanalysis (no potential gradients)"},{"name":"SpeciesActivity","value":"Ideal"},{"apiValue":"SHE","name":"PhysicsVsMaterialsReferenceElectrodePotential","value":"0 V"},{"description":"Streamline diffusion","name":"massStreamlineDiffusion"},{"description":"Crosswind diffusion","name":"massCrosswindDiffusion"},{"apiValue":"ApproximatedResidual","description":"Equation residual","name":"Residual","value":"Approximate residual"},{"apiValue":"DoCarmoAndGaleao","description":"Crosswind diffusion type","name":"CrosswindType","value":"Do Carmo and Galeão"},{"description":"Isotropic diffusion","name":"massIsotropicDiffusion"},{"apiValue":"noncons","description":"Convective term","name":"ConvectiveTerm","value":"Nonconservative form"},{"description":["Number of species","Concentrations"],"name":"cA","scalarReal":"2.0","value":["2","cA","cB"]},{"description":"Electric potential","name":"phis","value":"phis"}],"tag":"tcd","type":"Electroanalysis","windowType":1},{"apiClass":"MeshSequence","author":"COMSOL","created":"1696135407761","displayLabel":"Mesh 1","icon":"mesh.png","label":"Mesh 1","lastModified":"1696135445370","lastModifiedBy":"COMSOL","modelEntityPath":"/mesh/mesh1","settings":[{"apiValue":"automatic","description":"Type","name":"meshtype","value":"Physics-controlled mesh"},{"apiValue":"5.0","description":"Element size","name":"meshsize","value":"Normal"},{"apiValue":"visible","description":"Phys is visible","name":"physvisible","value":"Visible"}],"tag":"mesh1","type":"Mesh","windowType":1}],"settings":[{"apiValue":"useglobal","description":"Unit system","name":"basesystem","value":"Same as global system (SI)"},{"apiValue":"on","description":"Always define all frames","name":"defineAllFrames","value":"true"},{"apiValue":"automatic","description":"Geometry shape function","name":"sorderprop","value":"Automatic"},{"apiValue":"on","description":"Avoid inverted elements by curving interior domain elements","name":"curvedinterior","value":"true"}],"spaceDimension":1,"tag":"comp1","type":"Component[model]","windowType":1},{"apiClass":"Study","author":"COMSOL","created":"1696135407964","displayLabel":"Study 1","icon":"study.png","label":"Study 1","lastComputationDate":"1696135425385","lastComputationTime":"8468","lastComputationVersion":"COMSOL 6.2.0.259","lastModified":"1696135445370","lastModifiedBy":"COMSOL","modelEntityPath":"/study/std1","nodes":[{"apiClass":"StudyFeature","apiType":"Parametric","author":"COMSOL","created":"1696135415495","displayLabel":"Parametric Sweep","icon":"study_parametric_sweep.png","label":"Parametric Sweep","lastModified":"1696135445370","lastModifiedBy":"COMSOL","modelEntityPath":"/study/std1/feature/param","settings":[{"apiValue":"sparse","description":"Sweep type","name":"sweeptype","value":"Specified combinations"},{"apiValue":"all","description":["Keep solutions","Memory settings for jobs"],"name":"keepsol","value":"All"},{"apiValue":"off","description":"Plot","name":"plot","value":"false"},{"apiValue":"all","description":"Probes","name":"probesel","value":"All"},{"apiValue":"off","description":"Accumulated probe table","name":"useaccumtable","value":"false"},{"apiValue":"on","description":"Keep reduced-order models","name":"keeprom","value":"true"},{"apiValue":"parnameval","description":"Add to tag","name":"romtagsuffix","value":"Parameter name and value"},{"apiValue":"on","description":"Clear previous","name":"clearprevrom","value":"true"},{"apiValue":"on","description":"Keep the generating reduced-order model","name":"keepgenrom","value":"true"},{"apiValue":"auto","description":"Use parametric solver","name":"paramselect","value":"Automatic"},{"apiValue":"global","description":"Default solver sequence generation","name":"defsolvergen","value":"Using global parameters"},{"apiValue":"off","description":"Reuse solution from previous step","name":"reusesol","value":"false"}],"tag":"param","type":"Parametric_sweep","windowType":1},{"apiClass":"StudyFeature","apiType":"CyclicVoltammetry","author":"COMSOL","created":"1696135407964","displayLabel":"Cyclic Voltammetry","icon":"study_cyclic_voltammetry.png","label":"Cyclic Voltammetry","lastModified":"1696135445370","lastModifiedBy":"COMSOL","modelEntityPath":"/study/std1/feature/cyclv","settings":[{"apiValue":"off","description":"Tolerance","name":"usertol","value":"false"},{"apiValue":"off","description":"Plot","name":"plot","value":"false"},{"apiValue":"all","description":"Probes","name":"probesel","value":"All"},{"apiValue":"tsteps","description":"Update at","name":"probefreq","value":"Time steps taken by solver"},{"apiValue":"off","description":["Settings","Initial values of variables solved for"],"name":"useinitsol","value":"false"},{"apiValue":"off","description":["Settings","Values of variables not solved for"],"name":"usesol","value":"false"},{"apiValue":"none","description":"Adaptive mesh refinement","name":"timeadaption","value":"None"},{"apiValue":"off","description":"Auxiliary sweep","name":"useparam","value":"false"},{"apiValue":"off","description":"Automatic remeshing","name":"autoremesh","value":"false"}],"tag":"cyclv","type":"Cyclic_voltammetry","windowType":1},{"apiClass":"NonEntity","icon":"solver_sequence.png","label":"Solver Configurations","nodes":[{"apiClass":"SolverSequence","author":"COMSOL","created":"1696135415886","displayLabel":"Solution 1","icon":"solver_sequence1.png","label":"Solution 1","lastModified":"1696135445370","lastModifiedBy":"COMSOL","modelEntityPath":"/sol/sol1","name":"sol1","nodes":[{"apiClass":"SolverFeature","apiType":"StudyStep","author":"COMSOL","created":"1696135416354","displayLabel":"Compile Equations: Cyclic Voltammetry","icon":"solver_studystep.png","label":"Compile Equations: Cyclic Voltammetry","lastModified":"1696135445370","lastModifiedBy":"COMSOL","modelEntityPath":"/sol/sol1/feature/st1","settings":[{"apiValue":"cyclv","description":"Use study step","name":"studystep","value":"Cyclic Voltammetry"},{"apiValue":"off","description":"Split complex variables in real and imaginary parts","name":"splitcomplex","value":"false"},{"apiValue":"parent","description":"Partitioning method for distributed computing","name":"partmethod","value":"From parent"},{"apiValue":"off","description":"Save previous solution","name":"saveprevioussolution","value":"false"},{"apiValue":"all","description":"Use entities","name":"useent","value":"All"},{"apiValue":"off","description":"Keep warnings in stored log","name":"keeplog","value":"false"}],"tag":"st1","type":"Compile_equations","windowType":1},{"apiClass":"SolverFeature","apiType":"Variables","author":"COMSOL","created":"1696135416370","displayLabel":"Dependent Variables 1","icon":"solver_variables.png","label":"Dependent Variables 1","lastModified":"1696135445370","lastModifiedBy":"COMSOL","modelEntityPath":"/sol/sol1/feature/v1","nodes":[{"apiClass":"SolverFeature","apiType":"Field","author":"COMSOL","created":"1696135416776","displayLabel":"Concentration (comp1.cA)","icon":"solver_field.png","label":"Concentration (comp1.cA)","lastModified":"0","lastModifiedBy":"COMSOL","modelEntityPath":"/sol/sol1/feature/v1/feature/comp1_cA","settings":[{"apiValue":"parent","description":"Method","name":"scalemethod","value":"From parent"},{"apiValue":"parent","description":"Method","name":"resscalemethod","value":"From parent"},{"description":"Threshold for updating residual scale","name":"resscalethresh","scalarReal":"100.0","value":"100.0"}],"tag":"comp1_cA","type":"Field","windowType":1},{"apiClass":"SolverFeature","apiType":"Field","author":"COMSOL","created":"1696135416776","displayLabel":"Concentration (comp1.cB)","icon":"solver_field.png","label":"Concentration (comp1.cB)","lastModified":"0","lastModifiedBy":"COMSOL","modelEntityPath":"/sol/sol1/feature/v1/feature/comp1_cB","settings":[{"apiValue":"parent","description":"Method","name":"scalemethod","value":"From parent"},{"apiValue":"parent","description":"Method","name":"resscalemethod","value":"From parent"},{"description":"Threshold for updating residual scale","name":"resscalethresh","scalarReal":"100.0","value":"100.0"}],"tag":"comp1_cB","type":"Field","windowType":1}],"settings":[{"apiValue":"auto","description":"Method","name":"scalemethod","value":"Automatic"},{"apiValue":"manual","description":"Method","name":"resscalemethod","value":"Manual"},{"description":"Scale","name":"resscaleval","scalarReal":"1.0","value":"1.0"},{"description":"Threshold for updating residual scale","name":"resscalethresh","scalarReal":"100.0","value":"100.0"},{"apiValue":"auto","description":"Parameters","name":"initparametersmethod","value":"Automatic"},{"apiValue":"off","description":"Keep warnings in stored log","name":"keeplog","value":"false"}],"tag":"v1","type":"Dependent_variables","windowType":1},{"apiClass":"SolverFeature","apiType":"Time","author":"COMSOL","created":"1696135416776","displayLabel":"Time-Dependent Solver 1","icon":"solver_time.png","label":"Time-Dependent Solver 1","lastModified":"1696135445370","lastModifiedBy":"COMSOL","modelEntityPath":"/sol/sol1/feature/t1","nodes":[{"apiClass":"SolverFeature","apiType":"Advanced","author":"COMSOL","created":"1696135416792","displayLabel":"Advanced","icon":"solver_advanced.png","label":"Advanced","lastModified":"0","lastModifiedBy":"COMSOL","modelEntityPath":"/sol/sol1/feature/t1/feature/aDef","settings":[{"apiValue":"auto","description":"Matrix symmetry","name":"symmetric","value":"Automatic"},{"apiValue":"auto","description":"Matrix format","name":"matrixformat","value":"Automatic"},{"apiValue":"on","description":"Row equilibration","name":"rowscale","value":"true"},{"apiValue":"auto","description":"Null-space function","name":"nullfun","value":"Automatic"},{"description":"Orthonormal block limit","name":"orthonormallimit","scalarReal":"1.0E7","value":"10000000"},{"apiValue":"off","description":"Store last residual","name":"storeresidual","value":"false"},{"apiValue":"on","description":"Solver log","name":"convinfo","value":"Normal"},{"description":"Log sampling (wall-clock)","name":"logsampling","scalarReal":"0.005","value":"0.005"},{"apiValue":"frompreferences","description":"Recovery saving","name":"recoverysavinginfo","value":"From preferences"},{"apiValue":"frompreferences","description":"Force save of recovery file","name":"recoverysaveforce","value":"From preferences"},{"description":"Assembly block size","name":"blocksize","scalarReal":"1000.0","value":"1000"},{"apiValue":"off","description":"Assembly block size","name":"blocksizeactive","value":"false"},{"apiValue":"auto","description":"Use distributed solution for assembly","name":"assemdistrsol","value":"Automatic"},{"apiValue":"off","description":"Reuse sparsity pattern","name":"cachepattern","value":"false"},{"apiValue":"on","description":"Optimize data locality on cluster","name":"assemloc","value":"true"},{"apiValue":"off","description":"Use thread scheduling for matrix assembly","name":"optthread","value":"false"},{"apiValue":"off","description":"Use static distribution of assembly blocks","name":"statblockdistr","value":"false"},{"apiValue":"off","description":"Allow complex-valued output from functions with real input","name":"complexfun","value":"false"},{"apiValue":"on","description":"Stop when undefined mathematical operation is detected","name":"matherr","value":"true"},{"apiValue":"off","description":"Check for undefined numerical values after each operation","name":"checkmatherr","value":"false"},{"apiValue":"on","description":"Optimize element data initialization","name":"elemdatainit","value":"true"},{"description":"Drop tolerance for local matrix contributions","name":"assemtol","scalarReal":"1.0E-12","value":"1.0E-12"},{"apiValue":"off","description":"Manual control of reassembly","name":"keep","value":"false"}],"tag":"aDef","type":"Advanced","windowType":1},{"apiClass":"SolverFeature","apiType":"StopCondition","author":"COMSOL","created":"1696135416823","displayLabel":"Stop Condition 1","icon":"solver_stopcondition.png","label":"Stop Condition 1","lastModified":"0","lastModifiedBy":"COMSOL","modelEntityPath":"/sol/sol1/feature/t1/feature/st1","settings":[{"apiValue":"no","description":"Add solution","name":"storestopcondsol","value":"No"},{"apiValue":"off","description":"Add warning","name":"stopcondwarn","value":"false"}],"tag":"st1","type":"Stop_condition","windowType":1},{"apiClass":"SolverFeature","apiType":"FullyCoupled","author":"COMSOL","created":"1696135416886","displayLabel":"Fully Coupled 1","icon":"solver_fullycoupled.png","label":"Fully Coupled 1","lastModified":"1696135445370","lastModifiedBy":"COMSOL","modelEntityPath":"/sol/sol1/feature/t1/feature/fc1","settings":[{"apiValue":"const","description":"Nonlinear method","name":"dtech","value":"Constant (Newton)"},{"description":"Maximum number of iterations","name":"maxiter","scalarReal":"4.0","value":"4"},{"description":"Tolerance factor","name":"ntolfact","scalarReal":"1.0","value":"1"},{"apiValue":"off","description":"Termination criterion","name":"termonres","value":"Solution"},{"description":"Damping factor","name":"damp","scalarReal":"1.0","value":"1"},{"description":"Limit on nonlinear convergence rate","name":"ratelimit","scalarReal":"0.9","value":"0.9"},{"apiValue":"off","description":"Limit on nonlinear convergence rate","name":"ratelimitactive","value":"false"},{"apiValue":"once","description":"Jacobian update","name":"jtech","value":"Once per time step"},{"apiValue":"tol","description":"Termination technique","name":"ntermconst","value":"Tolerance"},{"apiValue":"off","description":"Use adaptive tolerance in the linear solver","name":"adapttol","value":"false"},{"apiValue":"aacc","description":"Stabilization and acceleration","name":"stabacc","value":"Anderson acceleration"},{"description":"Dimension of iteration space","name":"aaccdim","scalarReal":"5.0","value":"5"},{"description":"Mixing parameter","name":"aaccmix","scalarReal":"0.9","value":"0.9"},{"description":"Iteration delay","name":"aaccdelay","scalarReal":"1.0","value":"1"},{"description":"Threshold for Anderson step","name":"aaccfact","scalarReal":"10.0","value":"10"},{"apiValue":"off","description":"Plot","name":"plot","value":"false"},{"apiValue":"none","description":"Probes","name":"probesel","value":"None"}],"tag":"fc1","type":"Fully_coupled","windowType":1},{"apiClass":"SolverFeature","apiType":"Direct","author":"COMSOL","created":"1696135416886","displayLabel":"Direct (tcd)","icon":"solver_direct.png","label":"Direct (tcd)","lastModified":"0","lastModifiedBy":"COMSOL","modelEntityPath":"/sol/sol1/feature/t1/feature/d1","settings":[{"apiValue":"pardiso","description":"Solver","name":"linsolver","value":"PARDISO"},{"apiValue":"on","description":"Reuse preordering","name":"reusereorder","value":"true"},{"description":"Pivoting perturbation","name":"pivotperturb","scalarReal":"1.0E-8","value":"1.0E-8"},{"apiValue":"auto","description":"Out-of-core","name":"ooc","value":"Automatic"},{"description":"Memory fraction for out-of-core","name":"memfracooc","scalarReal":"0.99","value":"0.99"},{"apiValue":"auto","description":"In-core memory method","name":"incore","value":"Automatic"},{"description":"Minimum in-core memory (MB)","name":"minicmemory","scalarReal":"512.0","value":"512"},{"description":"Used fraction of total memory","name":"usetotmemory","scalarReal":"0.8","value":"0.8"},{"description":"Internal memory usage factor","name":"internalmemusage","scalarReal":"3.0","value":"3"},{"apiValue":"auto","description":"Preordering algorithm","name":"pardreorder","value":"Automatic"},{"apiValue":"auto","description":"Scheduling method","name":"pardschedule","value":"Auto"},{"apiValue":"on","description":"Row preordering","name":"pardrreorder","value":"true"},{"apiValue":"on","description":"Bunch–Kaufman pivoting","name":"pivotstrategy","value":"true"},{"apiValue":"on","description":"Multithreaded forward and backward solve","name":"pardmtsolve","value":"true"},{"apiValue":"on","description":"Parallel Direct Sparse Solver for Clusters","name":"clusterpardiso","value":"true"},{"apiValue":"auto","description":"Check error estimate","name":"errorchk","value":"Automatic"},{"description":"Factor in error estimate","name":"rhob","scalarReal":"1.0","value":"1"},{"apiValue":"on","description":"Iterative refinement","name":"iterrefine","value":"true"},{"description":"Maximum number of refinements","name":"maxrefinesteps","scalarReal":"15.0","value":"15"},{"description":"Error ratio bound","name":"errorratiobound","scalarReal":"0.5","value":"0.5"},{"apiValue":"off","description":"Use in nonlinear solver","name":"nliniterrefine","value":"false"}],"tag":"d1","type":"Direct","windowType":1}],"settings":[{"apiValue":"tsteps","description":"Times to store","name":"tout","value":"Steps taken by solver"},{"description":"Store every 𝑁th step","name":"tstepsstore","scalarReal":"1.0","value":"1"},{"apiValue":"scaled","description":"Global method","name":"atolglobalmethod","value":"Scaled"},{"apiValue":"factor","description":"Tolerance method","name":"atolglobalvaluemethod","value":"Factor"},{"description":"Tolerance factor","name":"atolglobalfactor","scalarReal":"0.1","value":"0.1"},{"apiValue":"auto","description":"Derivative tolerance method","name":"tderglobalmethod","value":"Automatic"},{"apiValue":"on","description":"Update scaled absolute tolerance","name":"ewtrescale","value":"true"},{"apiValue":"implicit","description":"Solver type","name":"odesolvertype","value":"Implicit"},{"apiValue":"bdf","description":"Method","name":"timemethod","value":"BDF"},{"apiValue":"free","description":"Steps taken by solver","name":"tstepsbdf","value":"Free"},{"apiValue":"on","description":"Interpolate solution at end time","name":"endtimeinterpolation","value":"true"},{"description":"Initial step","name":"initialstepbdf","value":"1e-3[V]/abs(v)"},{"apiValue":"on","description":"Initial step","name":"initialstepbdfactive","value":"true"},{"apiValue":"const","description":"Maximum step constraint","name":"maxstepconstraintbdf","value":"Constant"},{"description":"Maximum step","name":"maxstepbdf","value":"min(1e100,abs((E_vertex1-E_vertex2)/v))"},{"apiValue":"2","description":"Maximum BDF order","name":"maxorder","scalarReal":"2.0","value":"2"},{"apiValue":"1","description":"Minimum BDF order","name":"minorder","scalarReal":"1.0","value":"1"},{"description":"Event tolerance","name":"eventtol","scalarReal":"0.01","value":"0.01"},{"apiValue":"off","description":"Nonlinear controller","name":"stabcntrl","value":"false"},{"apiValue":"maybe","description":["Singular mass matrix","Algebraic variable settings"],"name":"masssingular","value":"Maybe"},{"apiValue":"bweuler","description":"Consistent initialization","name":"consistent","value":"Backward Euler"},{"description":"Fraction of initial step for Backward Euler","name":"bwinitstepfrac","scalarReal":"1.0E-5","value":"1.0E-5"},{"description":"Safety factor for Backward Euler","name":"bwinitfactor","scalarReal":"20.0","value":"20"},{"apiValue":"include","description":"Error estimation","name":"estrat","value":"Include algebraic"},{"apiValue":"off","description":"Rescale after initialization","name":"rescaleafterinitbw","value":"false"},{"apiValue":"on","description":"Store reaction forces","name":"reacf","value":"true"},{"apiValue":"off","description":"Use lumping when computing fluxes","name":"lumpedflux","value":"false"},{"apiValue":"on","description":"Store time derivatives","name":"storeudot","value":"true"},{"apiValue":"on","description":"Store solution before and after events","name":"eventout","value":"true"},{"apiValue":"off","description":"Allow complex numbers","name":"complex","value":"false"},{"apiValue":"off","description":"Periodic values of variables not solved for","name":"assumeperiodic","value":"false"},{"apiValue":"off","description":"Keep warnings in stored log","name":"keeplog","value":"false"},{"apiValue":"comp1_cA","description":"Variables","name":"fieldselection","value":"Concentration (comp1.cA)"}],"tag":"t1","type":"Time_dependent_solver","windowType":1}],"tag":"sol1","type":"Solution","windowType":1},{"apiClass":"SolverSequence","author":"COMSOL","created":"1696135416917","displayLabel":"Parametric Solutions 1","icon":"solver_sequence1.png","label":"Parametric Solutions 1","lastModified":"1696135445370","lastModifiedBy":"COMSOL","modelEntityPath":"/sol/sol2","name":"sol2","nodes":[{"apiClass":"SolverFeature","apiType":"StoreSolution","author":"COMSOL","created":"1696135419182","displayLabel":"v=0.001","icon":"solver_storesolution.png","label":"v=0.001","lastModified":"0","lastModifiedBy":"COMSOL","modelEntityPath":"/sol/sol2/feature/su1","name":"sol3","tag":"su1","type":"Solution_store","windowType":1},{"apiClass":"SolverFeature","apiType":"StoreSolution","author":"COMSOL","created":"1696135421214","displayLabel":"v=0.01","icon":"solver_storesolution.png","label":"v=0.01","lastModified":"0","lastModifiedBy":"COMSOL","modelEntityPath":"/sol/sol2/feature/su2","name":"sol4","tag":"su2","type":"Solution_store","windowType":1},{"apiClass":"SolverFeature","apiType":"StoreSolution","author":"COMSOL","created":"1696135423073","displayLabel":"v=0.1","icon":"solver_storesolution.png","label":"v=0.1","lastModified":"0","lastModifiedBy":"COMSOL","modelEntityPath":"/sol/sol2/feature/su3","name":"sol5","tag":"su3","type":"Solution_store","windowType":1},{"apiClass":"SolverFeature","apiType":"StoreSolution","author":"COMSOL","created":"1696135425260","displayLabel":"v=1","icon":"solver_storesolution.png","label":"v=1","lastModified":"0","lastModifiedBy":"COMSOL","modelEntityPath":"/sol/sol2/feature/su4","name":"sol6","tag":"su4","type":"Solution_store","windowType":1}],"tag":"sol2","type":"Solution","windowType":1}],"tag":"nonEntity3","windowType":1},{"apiClass":"NonEntity","icon":"job_configurations.png","label":"Job Configurations","nodes":[{"apiClass":"BatchFeature","apiType":"Parametric","author":"COMSOL","created":"1696135416901","displayLabel":"Parametric Sweep 1","icon":"parametric_sweep.png","label":"Parametric Sweep 1","lastModified":"1696135445370","lastModifiedBy":"COMSOL","modelEntityPath":"/batch/feature/p1","nodes":[{"apiClass":"BatchFeature","apiType":"Solutionseq","author":"COMSOL","created":"1696135416901","displayLabel":"Solution 1, Parametric Solutions 1","icon":"solver_sequence1.png","label":"Solution 1, Parametric Solutions 1","lastModified":"1696135425354","lastModifiedBy":"COMSOL","modelEntityPath":"/batch/feature/p1/feature/so1","settings":[{"apiValue":"on","description":"Clear previous","name":"clear","value":"Clear container initially"},{"apiValue":"parnameval","description":"Add to tag","name":"romtagsuffix","value":"Parameter name and value"},{"apiValue":"on","description":"Clear previous","name":"clearprevrom","value":"true"},{"apiValue":"on","description":"Keep the generating reduced-order model","name":"keepgenrom","value":"true"}],"tag":"so1","type":"Solution","windowType":1}],"settings":[{"description":"Stop condition","name":"stopcond"},{"apiValue":"off","description":"Keep solutions before and after stop condition","name":"keepbeforeandafter","value":"false"},{"apiValue":"on","description":"Stop if error","name":"err","value":"true"},{"apiValue":"off","description":"Postpone errors until end of sequence","name":"errignore","value":"false"},{"apiValue":"on","description":"Parametric sweep log","name":"convinfo","value":"Normal"},{"apiValue":"off","description":"Keep warnings in stored log","name":"keeplog","value":"false"}],"tag":"p1","type":"Parametric_sweep","windowType":1}],"tag":"nonEntity4","windowType":1}],"settings":[{"apiValue":"on","description":"Generate default plots","name":"genPlots","value":"true"},{"apiValue":"on","description":"Generate convergence plots","name":"genConv","value":"true"},{"apiValue":"off","description":"Store solution for all intermediate study steps","name":"storeSol","value":"false"},{"apiValue":"off","description":"Generate default plots for intermediately stored solutions","name":"genIntermediatePlots","value":"false"},{"apiValue":"off","description":"Plot the location of undefined values","name":"plotUndefVals","value":"false"},{"description":"Last computation time","name":"lastComputationTime","value":"8 s"},{"description":"Last computation date","name":"lastComputationDate","value":"Oct 1, 2023, 6:43:45 AM"},{"description":"Computed in version","name":"lastComputationVersion","value":"COMSOL 6.2.0.259"}],"tag":"std1","type":"Study","windowType":1},{"apiClass":"Results","author":"COMSOL","created":"1696135407636","displayLabel":"Results","icon":"post.png","label":"Results","lastModified":"0","lastModifiedBy":"COMSOL","modelEntityPath":"/result","nodes":[{"apiClass":"DatasetFeatureList","author":"COMSOL","created":"1696135407636","displayLabel":"Datasets","icon":"dataset.png","label":"Datasets","lastModified":"0","lastModifiedBy":"COMSOL","modelEntityPath":"/result/dataset","nodes":[{"apiClass":"DatasetFeature","apiType":"Solution","author":"COMSOL","created":"1696135415886","displayLabel":"Study 1/Solution 1","icon":"dataset_solution.png","label":"Study 1/Solution 1","lastModified":"1696135445370","lastModifiedBy":"COMSOL","modelEntityPath":"/result/dataset/dset1","name":"sol1","settings":[{"apiValue":"comp1","description":"Component","name":"comp","value":"Component 1 (comp1)"},{"apiValue":"material","description":"Frame","name":"frametype","value":"Material  (X, Y, Z)"},{"description":"Solution at angle (phase)","name":"phase","scalarReal":"0.0","value":"0"},{"description":"Scale factor","name":"scalefactor","scalarReal":"1.0","value":"1"}],"tag":"dset1","type":"Solution","windowType":1},{"apiClass":"DatasetFeature","apiType":"Solution","author":"COMSOL","created":"1696135416917","displayLabel":"Study 1/Parametric Solutions 1","icon":"dataset_solution.png","label":"Study 1/Parametric Solutions 1","lastModified":"1696135445370","lastModifiedBy":"COMSOL","modelEntityPath":"/result/dataset/dset2","name":"sol2","settings":[{"apiValue":"comp1","description":"Component","name":"comp","value":"Component 1 (comp1)"},{"apiValue":"material","description":"Frame","name":"frametype","value":"Material  (X, Y, Z)"},{"description":"Solution at angle (phase)","name":"phase","scalarReal":"0.0","value":"0"},{"description":"Scale factor","name":"scalefactor","scalarReal":"1.0","value":"1"}],"tag":"dset2","type":"Solution","windowType":1}],"tag":"dataset","type":"Datasets","windowType":1},{"apiClass":"NumericalFeatureList","author":"COMSOL","created":"1696135407636","displayLabel":"Derived Values","icon":"numerical_results.png","label":"Derived Values","lastModified":"0","lastModifiedBy":"COMSOL","modelEntityPath":"/result/numerical","tag":"numerical","type":"Derived_values","windowType":1},{"apiClass":"TableFeatureList","author":"COMSOL","created":"1696135407636","displayLabel":"Tables","icon":"post_table.png","label":"Tables","lastModified":"0","lastModifiedBy":"COMSOL","modelEntityPath":"/result/table","tag":"table","type":"Tables","windowType":1},{"apiClass":"ResultFeature","apiType":"PlotGroup1D","author":"COMSOL","created":"1696135425385","displayLabel":"Cyclic Voltammograms (tcd)","icon":"plot_group1d.png","label":"Cyclic Voltammograms (tcd)","lastModified":"1696135445370","lastModifiedBy":"COMSOL","modelEntityPath":"/result/feature/pg1","nodes":[{"apiClass":"ResultFeature","apiType":"Global","author":"COMSOL","created":"1696135425417","displayLabel":"Global 1","icon":"plot_global.png","label":"Global 1","lastModified":"1696135445370","lastModifiedBy":"COMSOL","modelEntityPath":"/result/feature/pg1/feature/glob1","settings":[{"apiValue":"off","description":"Plot on secondary y-axis","name":"plotonsecyaxis","value":"false"},{"apiValue":"none","description":"Title type","name":"titletype","value":"None"},{"apiValue":"level1","description":"Axis source data","name":"xdatasolnumtype","value":"Time"},{"apiValue":"expr","description":"Parameter","name":"xdata","value":"Expression"},{"description":"Expression","name":"xdataexpr","value":"root.comp1.tcd.phis_es1 "},{"apiValue":"V","description":"Unit","name":"xdataunit","value":"V"},{"description":"Description","name":"xdatadescr","value":"Electric Potential"},{"apiValue":"solid","description":["Line","Line style"],"name":"linestyle","value":"Solid"},{"apiValue":"continuous","description":"Function type","name":"functype","value":"Continuous"},{"apiValue":"cycle","description":"Color","name":"linecolor","value":"Cycle"},{"apiValue":"default","description":"Color cycle","name":"colorcycle","value":"Default"},{"apiValue":"1","description":"Width","name":"linewidth","scalarReal":"1.0","value":"1"},{"description":"Width","name":"linewidthslider","scalarReal":"1.0","value":"1"},{"apiValue":"none","description":["Marker","Line markers"],"name":"linemarker","value":"None"},{"description":"Refinement","name":"refine","scalarReal":"1.0","value":"1"},{"apiValue":"on","description":"Show legends","name":"legend","value":"true"},{"apiValue":"automatic","description":"Legends","name":"legendmethod","value":"Automatic"},{"apiValue":"off","description":["Label","Include"],"name":"autoplotlabel","value":"false"},{"apiValue":"on","description":"Solution","name":"autosolution","value":"true"},{"apiValue":"off","description":"Description","name":"autodescr","value":"false"},{"apiValue":"off","description":"Expression","name":"autoexpr","value":"false"},{"apiValue":"off","description":"Unit","name":"autounit","value":"false"},{"description":["Prefix","Prefix and suffix"],"name":"legendprefix"},{"description":"Suffix","name":"legendsuffix"},{"description":"Help","name":"legendallowexprshelp"},{"description":"Precision","name":"legendexprprecision","scalarReal":"3.0","value":"3"}],"tag":"glob1","type":"Global","windowType":1}],"settings":[{"apiValue":"off","description":"Save plot data","name":"savedatainmodel","value":"false"},{"apiValue":"auto","description":"Title type","name":"titletype","value":"Automatic"},{"apiValue":"fromtheme","description":"Color","name":"titlecolor","value":"From theme"},{"apiValue":"default","description":"Number format","name":"titlenumberformat","value":"Default"},{"description":"x-axis label","name":"xlabel","value":"Electric Potential (V)"},{"apiValue":"off","description":"x-axis label","name":"xlabelactive","value":"false"},{"description":"y-axis label","name":"ylabel","value":"Total Current (A)"},{"apiValue":"off","description":"y-axis label","name":"ylabelactive","value":"false"},{"apiValue":"off","description":"Two y-axes","name":"twoyaxes","value":"false"},{"apiValue":"off","description":"Flip the x- and y-axes","name":"switchxy","value":"false"},{"apiValue":"off","description":"Manual axis limits","name":"axislimits","value":"false"},{"apiValue":"off","description":"Preserve aspect ratio","name":"preserveaspect","value":"false"},{"apiValue":"off","description":"x-axis log scale","name":"xlog","value":"false"},{"apiValue":"off","description":"y-axis log scale","name":"ylog","value":"false"},{"apiValue":"on","description":"Show grid","name":"showgrid","value":"true"},{"apiValue":"off","description":"Manual spacing","name":"manualgrid","value":"false"},{"apiValue":"on","description":"Show legends","name":"showlegends","value":"true"},{"apiValue":"inside","description":"Layout","name":"legendlayout","value":"Inside graph axis area"},{"apiValue":"upperleft","description":"Position","name":"legendpos","value":"Upper left"},{"description":"Number of columns","name":"legendcolumncount","scalarReal":"1.0","value":"1"},{"description":"Maximum relative width","name":"legendmaxwidthinside","scalarReal":"0.5","value":"0.5"},{"apiValue":"off","description":"Manual axis settings","name":"axisactive","value":"false"},{"apiValue":"graphics","description":"Plot window","name":"window","value":"Graphics"}],"tag":"pg1","type":"1D_plot_group","windowType":1},{"apiClass":"ResultFeature","apiType":"PlotGroup1D","author":"COMSOL","created":"1696135425432","displayLabel":"Electrode Potential (tcd)","icon":"plot_group1d.png","label":"Electrode Potential (tcd)","lastModified":"1696135445370","lastModifiedBy":"COMSOL","modelEntityPath":"/result/feature/pg2","nodes":[{"apiClass":"ResultFeature","apiType":"Global","author":"COMSOL","created":"1696135425432","displayLabel":"Global 1","icon":"plot_global.png","label":"Global 1","lastModified":"1696135445370","lastModifiedBy":"COMSOL","modelEntityPath":"/result/feature/pg2/feature/glob1","settings":[{"apiValue":"off","description":"Plot on secondary y-axis","name":"plotonsecyaxis","value":"false"},{"apiValue":"auto","description":"Title type","name":"titletype","value":"Automatic"},{"apiValue":"level1","description":"Axis source data","name":"xdatasolnumtype","value":"Time"},{"apiValue":"solution","description":"Parameter","name":"xdata","value":"Time"},{"apiValue":"s","description":"Unit","name":"xdataparamunit","value":"s"},{"apiValue":"solid","description":["Line","Line style"],"name":"linestyle","value":"Solid"},{"apiValue":"continuous","description":"Function type","name":"functype","value":"Continuous"},{"apiValue":"cycle","description":"Color","name":"linecolor","value":"Cycle"},{"apiValue":"default","description":"Color cycle","name":"colorcycle","value":"Default"},{"apiValue":"1","description":"Width","name":"linewidth","scalarReal":"1.0","value":"1"},{"description":"Width","name":"linewidthslider","scalarReal":"1.0","value":"1"},{"apiValue":"none","description":["Marker","Line markers"],"name":"linemarker","value":"None"},{"description":"Refinement","name":"refine","scalarReal":"1.0","value":"1"},{"apiValue":"on","description":"Show legends","name":"legend","value":"true"},{"apiValue":"automatic","description":"Legends","name":"legendmethod","value":"Automatic"},{"apiValue":"off","description":["Label","Include"],"name":"autoplotlabel","value":"false"},{"apiValue":"on","description":"Solution","name":"autosolution","value":"true"},{"apiValue":"off","description":"Description","name":"autodescr","value":"false"},{"apiValue":"off","description":"Expression","name":"autoexpr","value":"false"},{"apiValue":"off","description":"Unit","name":"autounit","value":"false"},{"description":["Prefix","Prefix and suffix"],"name":"legendprefix"},{"description":"Suffix","name":"legendsuffix"},{"description":"Help","name":"legendallowexprshelp"},{"description":"Precision","name":"legendexprprecision","scalarReal":"3.0","value":"3"}],"tag":"glob1","type":"Global","windowType":1}],"settings":[{"apiValue":"off","description":"Save plot data","name":"savedatainmodel","value":"false"},{"apiValue":"none","description":"Title type","name":"titletype","value":"None"},{"description":"x-axis label","name":"xlabel","value":"Time (s)"},{"apiValue":"off","description":"x-axis label","name":"xlabelactive","value":"false"},{"description":"y-axis label","name":"ylabel","value":"Electric Potential (V)"},{"apiValue":"off","description":"y-axis label","name":"ylabelactive","value":"false"},{"apiValue":"off","description":"Two y-axes","name":"twoyaxes","value":"false"},{"apiValue":"off","description":"Flip the x- and y-axes","name":"switchxy","value":"false"},{"apiValue":"off","description":"Manual axis limits","name":"axislimits","value":"false"},{"apiValue":"off","description":"Preserve aspect ratio","name":"preserveaspect","value":"false"},{"apiValue":"off","description":"x-axis log scale","name":"xlog","value":"false"},{"apiValue":"off","description":"y-axis log scale","name":"ylog","value":"false"},{"apiValue":"on","description":"Show grid","name":"showgrid","value":"true"},{"apiValue":"off","description":"Manual spacing","name":"manualgrid","value":"false"},{"apiValue":"on","description":"Show legends","name":"showlegends","value":"true"},{"apiValue":"inside","description":"Layout","name":"legendlayout","value":"Inside graph axis area"},{"apiValue":"upperright","description":"Position","name":"legendpos","value":"Upper right"},{"description":"Number of columns","name":"legendcolumncount","scalarReal":"1.0","value":"1"},{"description":"Maximum relative width","name":"legendmaxwidthinside","scalarReal":"0.5","value":"0.5"},{"apiValue":"off","description":"Manual axis settings","name":"axisactive","value":"false"},{"apiValue":"graphics","description":"Plot window","name":"window","value":"Graphics"}],"tag":"pg2","type":"1D_plot_group","windowType":1},{"apiClass":"ResultFeature","apiType":"PlotGroup1D","author":"COMSOL","created":"1696135425448","displayLabel":"Average Current Density (tcd)","icon":"plot_group1d.png","label":"Average Current Density (tcd)","lastModified":"0","lastModifiedBy":"COMSOL","modelEntityPath":"/result/feature/pg3","nodes":[{"apiClass":"ResultFeature","apiType":"Global","author":"COMSOL","created":"1696135425448","displayLabel":"Global 1","icon":"plot_global.png","label":"Global 1","lastModified":"0","lastModifiedBy":"COMSOL","modelEntityPath":"/result/feature/pg3/feature/glob1","settings":[{"apiValue":"off","description":"Plot on secondary y-axis","name":"plotonsecyaxis","value":"false"},{"apiValue":"auto","description":"Title type","name":"titletype","value":"Automatic"},{"apiValue":"level1","description":"Axis source data","name":"xdatasolnumtype","value":"Time"},{"apiValue":"solution","description":"Parameter","name":"xdata","value":"Time"},{"apiValue":"s","description":"Unit","name":"xdataparamunit","value":"s"},{"apiValue":"solid","description":["Line","Line style"],"name":"linestyle","value":"Solid"},{"apiValue":"continuous","description":"Function type","name":"functype","value":"Continuous"},{"apiValue":"cycle","description":"Color","name":"linecolor","value":"Cycle"},{"apiValue":"default","description":"Color cycle","name":"colorcycle","value":"Default"},{"apiValue":"1","description":"Width","name":"linewidth","scalarReal":"1.0","value":"1"},{"description":"Width","name":"linewidthslider","scalarReal":"1.0","value":"1"},{"apiValue":"none","description":["Marker","Line markers"],"name":"linemarker","value":"None"},{"description":"Refinement","name":"refine","scalarReal":"1.0","value":"1"},{"apiValue":"on","description":"Show legends","name":"legend","value":"true"},{"apiValue":"automatic","description":"Legends","name":"legendmethod","value":"Automatic"},{"apiValue":"off","description":["Label","Include"],"name":"autoplotlabel","value":"false"},{"apiValue":"on","description":"Solution","name":"autosolution","value":"true"},{"apiValue":"on","description":"Description","name":"autodescr","value":"true"},{"apiValue":"off","description":"Expression","name":"autoexpr","value":"false"},{"apiValue":"off","description":"Unit","name":"autounit","value":"false"},{"description":["Prefix","Prefix and suffix"],"name":"legendprefix"},{"description":"Suffix","name":"legendsuffix"},{"description":"Help","name":"legendallowexprshelp"},{"description":"Precision","name":"legendexprprecision","scalarReal":"3.0","value":"3"}],"tag":"glob1","type":"Global","windowType":1}],"settings":[{"apiValue":"off","description":"Save plot data","name":"savedatainmodel","value":"false"},{"apiValue":"auto","description":"Title type","name":"titletype","value":"Automatic"},{"apiValue":"fromtheme","description":"Color","name":"titlecolor","value":"From theme"},{"apiValue":"default","description":"Number format","name":"titlenumberformat","value":"Default"},{"description":"x-axis label","name":"xlabel"},{"apiValue":"off","description":"x-axis label","name":"xlabelactive","value":"false"},{"description":"y-axis label","name":"ylabel"},{"apiValue":"off","description":"y-axis label","name":"ylabelactive","value":"false"},{"apiValue":"off","description":"Two y-axes","name":"twoyaxes","value":"false"},{"apiValue":"off","description":"Flip the x- and y-axes","name":"switchxy","value":"false"},{"apiValue":"off","description":"Manual axis limits","name":"axislimits","value":"false"},{"apiValue":"off","description":"Preserve aspect ratio","name":"preserveaspect","value":"false"},{"apiValue":"off","description":"x-axis log scale","name":"xlog","value":"false"},{"apiValue":"off","description":"y-axis log scale","name":"ylog","value":"false"},{"apiValue":"on","description":"Show grid","name":"showgrid","value":"true"},{"apiValue":"off","description":"Manual spacing","name":"manualgrid","value":"false"},{"apiValue":"on","description":"Show legends","name":"showlegends","value":"true"},{"apiValue":"inside","description":"Layout","name":"legendlayout","value":"Inside graph axis area"},{"apiValue":"upperright","description":"Position","name":"legendpos","value":"Upper right"},{"description":"Number of columns","name":"legendcolumncount","scalarReal":"1.0","value":"1"},{"description":"Maximum relative width","name":"legendmaxwidthinside","scalarReal":"0.5","value":"0.5"},{"apiValue":"off","description":"Manual axis settings","name":"axisactive","value":"false"},{"apiValue":"graphics","description":"Plot window","name":"window","value":"Graphics"}],"tag":"pg3","type":"1D_plot_group","windowType":1},{"apiClass":"ResultFeature","apiType":"PlotGroup1D","author":"COMSOL","created":"1696135425464","displayLabel":"Concentrations, All Species (tcd)","icon":"plot_group1d.png","label":"Concentrations, All Species (tcd)","lastModified":"0","lastModifiedBy":"COMSOL","modelEntityPath":"/result/feature/pg4","nodes":[{"apiClass":"ResultFeature","apiType":"LineGraph","author":"COMSOL","created":"1696135425464","displayLabel":"Species A","icon":"plot_line_graph.png","label":"Species A","lastModified":"1696135445370","lastModifiedBy":"COMSOL","modelEntityPath":"/result/feature/pg4/feature/lngr1","settings":[{"apiValue":"off","description":"Plot on secondary y-axis","name":"plotonsecyaxis","value":"false"},{"description":"Expression","name":"expr","value":"cA"},{"apiValue":"mol/m^3","description":"Unit","name":"unit","value":"mol/m^3"},{"description":"Description","name":"descr","value":"Concentration"},{"apiValue":"auto","description":"Title type","name":"titletype","value":"Automatic"},{"apiValue":"expr","description":"Parameter","name":"xdata","value":"Expression"},{"description":"Expression","name":"xdataexpr","value":"x"},{"apiValue":"m","description":"Unit","name":"xdataunit","value":"m"},{"description":"Description","name":"xdatadescr","value":"Spatial coordinates, x-component"},{"apiValue":"solid","description":["Line","Line style"],"name":"linestyle","value":"Solid"},{"apiValue":"cycle","description":"Color","name":"linecolor","value":"Cycle"},{"apiValue":"default","description":"Color cycle","name":"colorcycle","value":"Default"},{"apiValue":"1","description":"Width","name":"linewidth","scalarReal":"1.0","value":"1"},{"description":"Width","name":"linewidthslider","scalarReal":"1.0","value":"1"},{"apiValue":"none","description":["Marker","Line markers"],"name":"linemarker","value":"None"},{"apiValue":"on","description":"Show legends","name":"legend","value":"true"},{"apiValue":"automatic","description":"Legends","name":"legendmethod","value":"Automatic"},{"apiValue":"off","description":["Label","Include"],"name":"autoplotlabel","value":"false"},{"apiValue":"off","description":"Solution","name":"autosolution","value":"false"},{"apiValue":"off","description":"Description","name":"autodescr","value":"false"},{"apiValue":"off","description":"Expression","name":"autoexpr","value":"false"},{"apiValue":"off","description":"Unit","name":"autounit","value":"false"},{"description":["Prefix","Prefix and suffix"],"name":"legendprefix","value":"A "},{"description":"Suffix","name":"legendsuffix"},{"description":"Help","name":"legendallowexprshelp"},{"description":"Precision","name":"legendexprprecision","scalarReal":"3.0","value":"3"},{"apiValue":"normal","description":"Resolution","name":"resolution","value":"Normal"},{"apiValue":"material","description":"Smoothing","name":"smooth","value":"Inside material domains"},{"apiValue":"none","description":"Smoothing threshold","name":"threshold","value":"None"},{"apiValue":"off","description":"Recover","name":"recover","value":"false"}],"tag":"lngr1","type":"Line_graph","windowType":1},{"apiClass":"ResultFeature","apiType":"LineGraph","author":"COMSOL","created":"1696135425479","displayLabel":"Species B","icon":"plot_line_graph.png","label":"Species B","lastModified":"1696135445370","lastModifiedBy":"COMSOL","modelEntityPath":"/result/feature/pg4/feature/lngr2","settings":[{"apiValue":"off","description":"Plot on secondary y-axis","name":"plotonsecyaxis","value":"false"},{"description":"Expression","name":"expr","value":"cB"},{"apiValue":"mol/m^3","description":"Unit","name":"unit","value":"mol/m^3"},{"description":"Description","name":"descr","value":"Concentration"},{"apiValue":"auto","description":"Title type","name":"titletype","value":"Automatic"},{"apiValue":"expr","description":"Parameter","name":"xdata","value":"Expression"},{"description":"Expression","name":"xdataexpr","value":"x"},{"apiValue":"m","description":"Unit","name":"xdataunit","value":"m"},{"description":"Description","name":"xdatadescr","value":"Spatial coordinates, x-component"},{"apiValue":"solid","description":["Line","Line style"],"name":"linestyle","value":"Solid"},{"apiValue":"cycle","description":"Color","name":"linecolor","value":"Cycle"},{"apiValue":"default","description":"Color cycle","name":"colorcycle","value":"Default"},{"apiValue":"1","description":"Width","name":"linewidth","scalarReal":"1.0","value":"1"},{"description":"Width","name":"linewidthslider","scalarReal":"1.0","value":"1"},{"apiValue":"none","description":["Marker","Line markers"],"name":"linemarker","value":"None"},{"apiValue":"on","description":"Show legends","name":"legend","value":"true"},{"apiValue":"automatic","description":"Legends","name":"legendmethod","value":"Automatic"},{"apiValue":"off","description":["Label","Include"],"name":"autoplotlabel","value":"false"},{"apiValue":"off","description":"Solution","name":"autosolution","value":"false"},{"apiValue":"off","description":"Description","name":"autodescr","value":"false"},{"apiValue":"off","description":"Expression","name":"autoexpr","value":"false"},{"apiValue":"off","description":"Unit","name":"autounit","value":"false"},{"description":["Prefix","Prefix and suffix"],"name":"legendprefix","value":"B "},{"description":"Suffix","name":"legendsuffix"},{"description":"Help","name":"legendallowexprshelp"},{"description":"Precision","name":"legendexprprecision","scalarReal":"3.0","value":"3"},{"apiValue":"normal","description":"Resolution","name":"resolution","value":"Normal"},{"apiValue":"material","description":"Smoothing","name":"smooth","value":"Inside material domains"},{"apiValue":"none","description":"Smoothing threshold","name":"threshold","value":"None"},{"apiValue":"off","description":"Recover","name":"recover","value":"false"}],"tag":"lngr2","type":"Line_graph","windowType":1}],"settings":[{"apiValue":"off","description":"Save plot data","name":"savedatainmodel","value":"false"},{"apiValue":"manual","description":"Title type","name":"titletype","value":"Manual"},{"apiValue":"fromtheme","description":"Color","name":"titlecolor","value":"From theme"},{"apiValue":"default","description":"Number format","name":"titlenumberformat","value":"Default"},{"description":"Title","name":"title"},{"description":"Parameter indicator","name":"paramindicator"},{"description":"Help","name":"help1"},{"description":"Help","name":"help2"},{"description":"Help","name":"help3"},{"description":"x-axis label","name":"xlabel"},{"apiValue":"off","description":"x-axis label","name":"xlabelactive","value":"false"},{"description":"y-axis label","name":"ylabel"},{"apiValue":"off","description":"y-axis label","name":"ylabelactive","value":"false"},{"apiValue":"off","description":"Two y-axes","name":"twoyaxes","value":"false"},{"apiValue":"off","description":"Flip the x- and y-axes","name":"switchxy","value":"false"},{"apiValue":"off","description":"Manual axis limits","name":"axislimits","value":"false"},{"apiValue":"off","description":"Preserve aspect ratio","name":"preserveaspect","value":"false"},{"apiValue":"off","description":"x-axis log scale","name":"xlog","value":"false"},{"apiValue":"off","description":"y-axis log scale","name":"ylog","value":"false"},{"apiValue":"on","description":"Show grid","name":"showgrid","value":"true"},{"apiValue":"off","description":"Manual spacing","name":"manualgrid","value":"false"},{"apiValue":"on","description":"Show legends","name":"showlegends","value":"true"},{"apiValue":"inside","description":"Layout","name":"legendlayout","value":"Inside graph axis area"},{"apiValue":"upperright","description":"Position","name":"legendpos","value":"Upper right"},{"description":"Number of columns","name":"legendcolumncount","scalarReal":"1.0","value":"1"},{"description":"Maximum relative width","name":"legendmaxwidthinside","scalarReal":"0.5","value":"0.5"},{"apiValue":"off","description":"Manual axis settings","name":"axisactive","value":"false"},{"apiValue":"graphics","description":"Plot window","name":"window","value":"Graphics"}],"tag":"pg4","type":"1D_plot_group","windowType":1},{"apiClass":"ResultFeature","apiType":"PlotGroup1D","author":"COMSOL","created":"1696135425495","displayLabel":"Concentration, A (tcd)","icon":"plot_group1d.png","label":"Concentration, A (tcd)","lastModified":"0","lastModifiedBy":"COMSOL","modelEntityPath":"/result/feature/pg5","nodes":[{"apiClass":"ResultFeature","apiType":"LineGraph","author":"COMSOL","created":"1696135425495","displayLabel":"Line Graph 1","icon":"plot_line_graph.png","label":"Line Graph 1","lastModified":"1696135445370","lastModifiedBy":"COMSOL","modelEntityPath":"/result/feature/pg5/feature/lngr1","settings":[{"apiValue":"off","description":"Plot on secondary y-axis","name":"plotonsecyaxis","value":"false"},{"description":"Expression","name":"expr","value":"cA"},{"apiValue":"mol/m^3","description":"Unit","name":"unit","value":"mol/m^3"},{"description":"Description","name":"descr","value":"Concentration"},{"apiValue":"auto","description":"Title type","name":"titletype","value":"Automatic"},{"apiValue":"expr","description":"Parameter","name":"xdata","value":"Expression"},{"description":"Expression","name":"xdataexpr","value":"x"},{"apiValue":"m","description":"Unit","name":"xdataunit","value":"m"},{"description":"Description","name":"xdatadescr","value":"Spatial coordinates, x-component"},{"apiValue":"solid","description":["Line","Line style"],"name":"linestyle","value":"Solid"},{"apiValue":"cycle","description":"Color","name":"linecolor","value":"Cycle"},{"apiValue":"default","description":"Color cycle","name":"colorcycle","value":"Default"},{"apiValue":"1","description":"Width","name":"linewidth","scalarReal":"1.0","value":"1"},{"description":"Width","name":"linewidthslider","scalarReal":"1.0","value":"1"},{"apiValue":"none","description":["Marker","Line markers"],"name":"linemarker","value":"None"},{"apiValue":"off","description":"Show legends","name":"legend","value":"false"},{"apiValue":"automatic","description":"Legends","name":"legendmethod","value":"Automatic"},{"apiValue":"off","description":["Label","Include"],"name":"autoplotlabel","value":"false"},{"apiValue":"on","description":"Solution","name":"autosolution","value":"true"},{"apiValue":"off","description":"Description","name":"autodescr","value":"false"},{"apiValue":"off","description":"Expression","name":"autoexpr","value":"false"},{"apiValue":"off","description":"Unit","name":"autounit","value":"false"},{"description":["Prefix","Prefix and suffix"],"name":"legendprefix"},{"description":"Suffix","name":"legendsuffix"},{"description":"Help","name":"legendallowexprshelp"},{"description":"Precision","name":"legendexprprecision","scalarReal":"3.0","value":"3"},{"apiValue":"normal","description":"Resolution","name":"resolution","value":"Normal"},{"apiValue":"material","description":"Smoothing","name":"smooth","value":"Inside material domains"},{"apiValue":"none","description":"Smoothing threshold","name":"threshold","value":"None"},{"apiValue":"off","description":"Recover","name":"recover","value":"false"}],"tag":"lngr1","type":"Line_graph","windowType":1}],"settings":[{"apiValue":"off","description":"Save plot data","name":"savedatainmodel","value":"false"},{"apiValue":"custom","description":"Title type","name":"titletype","value":"Custom"},{"apiValue":"fromtheme","description":"Color","name":"titlecolor","value":"From theme"},{"apiValue":"default","description":"Number format","name":"titlenumberformat","value":"Default"},{"apiValue":"off","description":["Dataset","Solution"],"name":"datasetintitle","value":"false"},{"apiValue":"off","description":"Phase","name":"phaseintitle","value":"false"},{"apiValue":"off","description":"Filename","name":"filenameintitle","value":"false"},{"apiValue":"off","description":"Date","name":"dateintitle","value":"false"},{"apiValue":"off","description":"Time","name":"timeintitle","value":"false"},{"description":["Prefix","User"],"name":"prefixintitle","value":"Species A:"},{"description":"Suffix","name":"suffixintitle"},{"apiValue":"off","description":["Type","Type and data"],"name":"typeintitle","value":"false"},{"apiValue":"on","description":"Description","name":"descriptionintitle","value":"true"},{"apiValue":"off","description":"Expression","name":"expressionintitle","value":"false"},{"apiValue":"on","description":"Unit","name":"unitintitle","value":"true"},{"apiValue":"on","description":["Use parameter indicator for solution and phase","Layout"],"name":"titleparamindicator","value":"true"},{"description":"x-axis label","name":"xlabel"},{"apiValue":"off","description":"x-axis label","name":"xlabelactive","value":"false"},{"description":"y-axis label","name":"ylabel"},{"apiValue":"off","description":"y-axis label","name":"ylabelactive","value":"false"},{"apiValue":"off","description":"Two y-axes","name":"twoyaxes","value":"false"},{"apiValue":"off","description":"Flip the x- and y-axes","name":"switchxy","value":"false"},{"apiValue":"off","description":"Manual axis limits","name":"axislimits","value":"false"},{"apiValue":"off","description":"Preserve aspect ratio","name":"preserveaspect","value":"false"},{"apiValue":"off","description":"x-axis log scale","name":"xlog","value":"false"},{"apiValue":"off","description":"y-axis log scale","name":"ylog","value":"false"},{"apiValue":"on","description":"Show grid","name":"showgrid","value":"true"},{"apiValue":"off","description":"Manual spacing","name":"manualgrid","value":"false"},{"apiValue":"on","description":"Show legends","name":"showlegends","value":"true"},{"apiValue":"inside","description":"Layout","name":"legendlayout","value":"Inside graph axis area"},{"apiValue":"upperright","description":"Position","name":"legendpos","value":"Upper right"},{"description":"Number of columns","name":"legendcolumncount","scalarReal":"1.0","value":"1"},{"description":"Maximum relative width","name":"legendmaxwidthinside","scalarReal":"0.5","value":"0.5"},{"apiValue":"off","description":"Manual axis settings","name":"axisactive","value":"false"},{"apiValue":"graphics","description":"Plot window","name":"window","value":"Graphics"}],"tag":"pg5","type":"1D_plot_group","windowType":1},{"apiClass":"ResultFeature","apiType":"PlotGroup1D","author":"COMSOL","created":"1696135425495","displayLabel":"Concentration, B (tcd)","icon":"plot_group1d.png","label":"Concentration, B (tcd)","lastModified":"0","lastModifiedBy":"COMSOL","modelEntityPath":"/result/feature/pg6","nodes":[{"apiClass":"ResultFeature","apiType":"LineGraph","author":"COMSOL","created":"1696135425510","displayLabel":"Line Graph 1","icon":"plot_line_graph.png","label":"Line Graph 1","lastModified":"1696135445370","lastModifiedBy":"COMSOL","modelEntityPath":"/result/feature/pg6/feature/lngr1","settings":[{"apiValue":"off","description":"Plot on secondary y-axis","name":"plotonsecyaxis","value":"false"},{"description":"Expression","name":"expr","value":"cB"},{"apiValue":"mol/m^3","description":"Unit","name":"unit","value":"mol/m^3"},{"description":"Description","name":"descr","value":"Concentration"},{"apiValue":"auto","description":"Title type","name":"titletype","value":"Automatic"},{"apiValue":"expr","description":"Parameter","name":"xdata","value":"Expression"},{"description":"Expression","name":"xdataexpr","value":"x"},{"apiValue":"m","description":"Unit","name":"xdataunit","value":"m"},{"description":"Description","name":"xdatadescr","value":"Spatial coordinates, x-component"},{"apiValue":"solid","description":["Line","Line style"],"name":"linestyle","value":"Solid"},{"apiValue":"cycle","description":"Color","name":"linecolor","value":"Cycle"},{"apiValue":"default","description":"Color cycle","name":"colorcycle","value":"Default"},{"apiValue":"1","description":"Width","name":"linewidth","scalarReal":"1.0","value":"1"},{"description":"Width","name":"linewidthslider","scalarReal":"1.0","value":"1"},{"apiValue":"none","description":["Marker","Line markers"],"name":"linemarker","value":"None"},{"apiValue":"off","description":"Show legends","name":"legend","value":"false"},{"apiValue":"automatic","description":"Legends","name":"legendmethod","value":"Automatic"},{"apiValue":"off","description":["Label","Include"],"name":"autoplotlabel","value":"false"},{"apiValue":"on","description":"Solution","name":"autosolution","value":"true"},{"apiValue":"off","description":"Description","name":"autodescr","value":"false"},{"apiValue":"off","description":"Expression","name":"autoexpr","value":"false"},{"apiValue":"off","description":"Unit","name":"autounit","value":"false"},{"description":["Prefix","Prefix and suffix"],"name":"legendprefix"},{"description":"Suffix","name":"legendsuffix"},{"description":"Help","name":"legendallowexprshelp"},{"description":"Precision","name":"legendexprprecision","scalarReal":"3.0","value":"3"},{"apiValue":"normal","description":"Resolution","name":"resolution","value":"Normal"},{"apiValue":"material","description":"Smoothing","name":"smooth","value":"Inside material domains"},{"apiValue":"none","description":"Smoothing threshold","name":"threshold","value":"None"},{"apiValue":"off","description":"Recover","name":"recover","value":"false"}],"tag":"lngr1","type":"Line_graph","windowType":1}],"settings":[{"apiValue":"off","description":"Save plot data","name":"savedatainmodel","value":"false"},{"apiValue":"custom","description":"Title type","name":"titletype","value":"Custom"},{"apiValue":"fromtheme","description":"Color","name":"titlecolor","value":"From theme"},{"apiValue":"default","description":"Number format","name":"titlenumberformat","value":"Default"},{"apiValue":"off","description":["Dataset","Solution"],"name":"datasetintitle","value":"false"},{"apiValue":"off","description":"Phase","name":"phaseintitle","value":"false"},{"apiValue":"off","description":"Filename","name":"filenameintitle","value":"false"},{"apiValue":"off","description":"Date","name":"dateintitle","value":"false"},{"apiValue":"off","description":"Time","name":"timeintitle","value":"false"},{"description":["Prefix","User"],"name":"prefixintitle","value":"Species B:"},{"description":"Suffix","name":"suffixintitle"},{"apiValue":"off","description":["Type","Type and data"],"name":"typeintitle","value":"false"},{"apiValue":"on","description":"Description","name":"descriptionintitle","value":"true"},{"apiValue":"off","description":"Expression","name":"expressionintitle","value":"false"},{"apiValue":"on","description":"Unit","name":"unitintitle","value":"true"},{"apiValue":"on","description":["Use parameter indicator for solution and phase","Layout"],"name":"titleparamindicator","value":"true"},{"description":"x-axis label","name":"xlabel"},{"apiValue":"off","description":"x-axis label","name":"xlabelactive","value":"false"},{"description":"y-axis label","name":"ylabel"},{"apiValue":"off","description":"y-axis label","name":"ylabelactive","value":"false"},{"apiValue":"off","description":"Two y-axes","name":"twoyaxes","value":"false"},{"apiValue":"off","description":"Flip the x- and y-axes","name":"switchxy","value":"false"},{"apiValue":"off","description":"Manual axis limits","name":"axislimits","value":"false"},{"apiValue":"off","description":"Preserve aspect ratio","name":"preserveaspect","value":"false"},{"apiValue":"off","description":"x-axis log scale","name":"xlog","value":"false"},{"apiValue":"off","description":"y-axis log scale","name":"ylog","value":"false"},{"apiValue":"on","description":"Show grid","name":"showgrid","value":"true"},{"apiValue":"off","description":"Manual spacing","name":"manualgrid","value":"false"},{"apiValue":"on","description":"Show legends","name":"showlegends","value":"true"},{"apiValue":"inside","description":"Layout","name":"legendlayout","value":"Inside graph axis area"},{"apiValue":"upperright","description":"Position","name":"legendpos","value":"Upper right"},{"description":"Number of columns","name":"legendcolumncount","scalarReal":"1.0","value":"1"},{"description":"Maximum relative width","name":"legendmaxwidthinside","scalarReal":"0.5","value":"0.5"},{"apiValue":"off","description":"Manual axis settings","name":"axisactive","value":"false"},{"apiValue":"graphics","description":"Plot window","name":"window","value":"Graphics"}],"tag":"pg6","type":"1D_plot_group","windowType":1},{"apiClass":"ExportFeatureList","author":"COMSOL","created":"1696135407636","displayLabel":"Export","icon":"results_export.png","label":"Export","lastModified":"0","lastModifiedBy":"COMSOL","modelEntityPath":"/result/export","tag":"export","type":"Export[noun]","windowType":1},{"apiClass":"ReportFeatureList","author":"COMSOL","created":"1696135407682","displayLabel":"Reports","icon":"results_report.png","label":"Reports","lastModified":"0","lastModifiedBy":"COMSOL","modelEntityPath":"/result/report","tag":"report","type":"Reports","windowType":1}],"settings":[{"apiValue":"off","description":"Only plot when requested","name":"onlyplotwhenrequested","value":"false"},{"apiValue":"off","description":"Recompute all plot data after solving","name":"autoregenerateplot","value":"false"},{"apiValue":"off","description":"Reevaluate all evaluation groups after solving","name":"autoregenerateevalgroups","value":"false"},{"apiValue":"AUTOMATIC","description":"Save plot data","name":"saveplotdatainmodel","value":"Automatic"}],"tag":"result","type":"Results","windowType":1}],"settings":[{"apiValue":"SI","description":"Unit system","name":"basesystem","value":"SI"},{"apiValue":"automatic","description":"Graphics color theme","name":"colortheme","value":"Default from application theme (Default)"},{"apiValue":"automatic","description":"Image export color theme","name":"imagecolortheme","value":"Default from image export theme (Default)"},{"apiValue":"automatic","description":["Family","Font"],"name":"fontfamily","value":"Default from preferences (Vera)"},{"apiValue":"default","description":"Size","name":"fontsize","value":"Default size"},{"apiValue":"off","description":"Ask to save application when closing","name":"asktosave","value":"false"},{"apiValue":"edit","description":"When starting with COMSOL Multiphysics","name":"startmode","value":"Edit application"},{"apiValue":"off","description":"Ignore license errors during launch","name":"ignorelicenseerrors","value":"false"},{"apiValue":"off","description":"Use built-in COMSOL resources","name":"localize","value":"false"}],"tag":"Model","title":"Cyclic Voltammetry at a Macroelectrode in 1D","type":"Root","windowType":1}